src/__init__.py
src/hello.py
rcm_hello_py-0.1.1.dist-info/LICENSE
rcm_hello_py-0.1.1.dist-info/METADATA
rcm_hello_py-0.1.1.dist-info/WHEEL
rcm_hello_py-0.1.1.dist-info/top_level.txt
rcm_hello_py-0.1.1.dist-info/RECORD
