Metadata-Version: 2.1
Name: rcm-hello-py
Version: 0.1.1
Summary: A dummy python project for testing
Home-page: https://gitlab.com/residential-climate-monitoring/hello-py
Author: Pim Hazebroek
Author-email: author@example.com
License: UNKNOWN
Platform: UNKNOWN
Classifier: Programming Language :: Python :: 3
Classifier: License :: OSI Approved :: MIT License
Classifier: Operating System :: OS Independent
Requires-Python: >=3.6
